mife/__init__.py
mife/common.py
mife/data/__init__.py
mife/data/curve25519.py
mife/data/fastecdsa_wrapper.py
mife/data/group.py
mife/data/matrix.py
mife/data/paillier.py
mife/data/pairing.py
mife/data/pyecc_bn128_wrapper.py
mife/data/zmod.py
mife/data/zmod_r.py
mife/misc/__init__.py
mife/misc/cprf.py
mife/multi/__init__.py
mife/multi/damgard.py
mife/multiclient/__init__.py
mife/multiclient/damgard.py
mife/multiclient/decentralized/__init__.py
mife/multiclient/decentralized/ddh.py
mife/multiclient/decentralized/palia.py
mife/multiclient/rom/__init__.py
mife/multiclient/rom/ddh.py
mife/single/__init__.py
mife/single/damgard.py
mife/single/lwe.py
mife/single/fhiding/ddh.py
mife/single/quadratic/ddh.py
mife/single/selective/__init__.py
mife/single/selective/ddh.py
mife/single/selective/lwe.py
pymife-0.0.13.dist-info/METADATA
pymife-0.0.13.dist-info/WHEEL
pymife-0.0.13.dist-info/licenses/LICENSE
pymife-0.0.13.dist-info/RECORD
