Metadata-Version: 2.3
Name: pymife
Version: 0.0.13
Summary: Python Functional Encryption Library
Author-email: mechfrog88 <kelzzin2@gmail.com>
License-File: LICENSE
Classifier: License :: OSI Approved :: MIT License
Classifier: Operating System :: OS Independent
Classifier: Programming Language :: Python :: 3
Requires-Python: >=3.9
Requires-Dist: gmpy2>=2.1.5
Requires-Dist: numpy>=1.26.4
Requires-Dist: pycryptodome>=3.20.0
Provides-Extra: extragroup
Requires-Dist: fastecdsa>=2.3.0; extra == 'extragroup'
Requires-Dist: py-ecc>=7.0.0; extra == 'extragroup'
